neutron_lib/__init__.py
neutron_lib/_i18n.py
neutron_lib/constants.py
neutron_lib/context.py
neutron_lib/fixture.py
neutron_lib/rpc.py
neutron_lib/version.py
neutron_lib/worker.py
neutron_lib/agent/__init__.py
neutron_lib/agent/constants.py
neutron_lib/agent/extension.py
neutron_lib/agent/l2_extension.py
neutron_lib/agent/l3_extension.py
neutron_lib/agent/topics.py
neutron_lib/agent/common/__init__.py
neutron_lib/agent/common/constants.py
neutron_lib/agent/common/utils.py
neutron_lib/agent/linux/__init__.py
neutron_lib/agent/linux/interface.py
neutron_lib/api/__init__.py
neutron_lib/api/attributes.py
neutron_lib/api/converters.py
neutron_lib/api/extensions.py
neutron_lib/api/faults.py
neutron_lib/api/definitions/__init__.py
neutron_lib/api/definitions/_dummy.py
neutron_lib/api/definitions/address_group.py
neutron_lib/api/definitions/address_scope.py
neutron_lib/api/definitions/agent.py
neutron_lib/api/definitions/agent_resources_synced.py
neutron_lib/api/definitions/agent_sort_key.py
neutron_lib/api/definitions/allowedaddresspairs.py
neutron_lib/api/definitions/allowedaddresspairs_atomic.py
neutron_lib/api/definitions/auto_allocated_topology.py
neutron_lib/api/definitions/availability_zone.py
neutron_lib/api/definitions/availability_zone_filter.py
neutron_lib/api/definitions/base.py
neutron_lib/api/definitions/bgp.py
neutron_lib/api/definitions/bgp_4byte_asn.py
neutron_lib/api/definitions/bgp_dragentscheduler.py
neutron_lib/api/definitions/bgpvpn.py
neutron_lib/api/definitions/bgpvpn_routes_control.py
neutron_lib/api/definitions/bgpvpn_stdattrs.py
neutron_lib/api/definitions/bgpvpn_stdattrs_net_assoc.py
neutron_lib/api/definitions/bgpvpn_stdattrs_port_assoc.py
neutron_lib/api/definitions/bgpvpn_stdattrs_router_assoc.py
neutron_lib/api/definitions/bgpvpn_vni.py
neutron_lib/api/definitions/constants.py
neutron_lib/api/definitions/data_plane_status.py
neutron_lib/api/definitions/default_subnetpools.py
neutron_lib/api/definitions/dhcpagentscheduler.py
neutron_lib-3.23.0.dist-info/licenses/AUTHORS
neutron_lib-3.23.0.dist-info/licenses/LICENSE
neutron_lib-3.23.0.dist-info/METADATA
neutron_lib-3.23.0.dist-info/WHEEL
neutron_lib-3.23.0.dist-info/entry_points.txt
neutron_lib-3.23.0.dist-info/pbr.json
neutron_lib-3.23.0.dist-info/top_level.txt
neutron_lib-3.23.0.dist-info/RECORD
