Metadata-Version: 2.4
Name: neutron-lib
Version: 3.23.0
Summary: Neutron shared routines and utilities
Home-page: https://docs.openstack.org/neutron-lib/latest/
Author: OpenStack
Author-email: openstack-discuss@lists.openstack.org
Classifier: Environment :: OpenStack
Classifier: Intended Audience :: Information Technology
Classifier: Intended Audience :: System Administrators
Classifier: License :: OSI Approved :: Apache Software License
Classifier: Operating System :: POSIX :: Linux
Classifier: Programming Language :: Python
Classifier: Programming Language :: Python :: 3
Classifier: Programming Language :: Python :: 3.9
Classifier: Programming Language :: Python :: 3.10
Classifier: Programming Language :: Python :: 3.11
Classifier: Programming Language :: Python :: 3.12
Requires-Python: >=3.9
License-File: LICENSE
License-File: AUTHORS
Requires-Dist: pbr>=4.0.0
Requires-Dist: SQLAlchemy>=1.2.0
Requires-Dist: pecan>=1.0.0
Requires-Dist: keystoneauth1>=3.14.0
Requires-Dist: netaddr>=0.7.18
Requires-Dist: stevedore>=5.6.0
Requires-Dist: os-ken>=0.3.0
Requires-Dist: oslo.concurrency>=3.26.0
Requires-Dist: oslo.config>=8.0.0
Requires-Dist: oslo.context>=2.22.0
Requires-Dist: oslo.db>=12.1.0
Requires-Dist: oslo.i18n>=3.20.0
Requires-Dist: oslo.log>=4.3.0
Requires-Dist: oslo.messaging>=14.2.0
Requires-Dist: oslo.policy>=4.5.0
Requires-Dist: oslo.serialization>=2.25.0
Requires-Dist: oslo.service>=1.24.0
Requires-Dist: oslo.utils>=7.0.0
Requires-Dist: oslo.versionedobjects>=1.31.2
Requires-Dist: osprofiler>=1.4.0
Requires-Dist: setproctitle>=1.1.10
Requires-Dist: WebOb>=1.7.1
Requires-Dist: os-traits>=0.9.0
Requires-Dist: debtcollector>=3.0.0
Dynamic: author
Dynamic: author-email
Dynamic: classifier
Dynamic: description
Dynamic: home-page
Dynamic: license-file
Dynamic: requires-dist
Dynamic: requires-python
Dynamic: summary
